qjackcapture/__main__.py
qjackcapture/app.py
qjackcapture/resources_rc.py
qjackcapture/ui_mainwindow.py
qjackcapture/userdirs.py
qjackcapture/version.py
QJackCapture-0.2.1.dist-info/LICENSE
QJackCapture-0.2.1.dist-info/METADATA
QJackCapture-0.2.1.dist-info/WHEEL
QJackCapture-0.2.1.dist-info/entry_points.txt
QJackCapture-0.2.1.dist-info/top_level.txt
QJackCapture-0.2.1.dist-info/RECORD
