Metadata-Version: 2.1
Name: QJackCapture
Version: 0.2.1
Summary: A GUI for easy recording of JACK audio sources using jack_capture.
Home-page: https://github.com/SpotlightKid/qjackcapture
Author: Filipe Coelho (falkTX)
Author-email: falktx@falktx.com
Maintainer: Christopher Arndt
Maintainer-email: chris@chrisarndt.de
License: GPLv2+
Keywords: audio,jack,midi
Classifier: Development Status :: 4 - Beta
Classifier: Environment :: X11 Applications :: Qt
Classifier: Intended Audience :: End Users/Desktop
Classifier: License :: OSI Approved :: GNU General Public License v2 or later (GPLv2+)
Classifier: Operating System :: MacOS :: MacOS X
Classifier: Operating System :: Microsoft :: Windows
Classifier: Operating System :: POSIX :: Linux
Classifier: Programming Language :: Python
Classifier: Programming Language :: Python :: 3
Classifier: Programming Language :: Python :: 3.6
Classifier: Programming Language :: Python :: 3.7
Classifier: Programming Language :: Python :: 3.8
Classifier: Programming Language :: Python :: 3.9
Classifier: Programming Language :: Python :: 3 :: Only
Classifier: Topic :: Multimedia :: Sound/Audio
Classifier: Topic :: Utilities
License-File: LICENSE
Requires-Dist: natsort
Requires-Dist: pyjacklib
Requires-Dist: PyQt5
